engagesdk/__init__.py
engagesdk/base.py
engagesdk/engage.py
engagesdk/error.py
engagesdk/user.py
engagesdk/version.py
engagesdk-1.1.dist-info/METADATA
engagesdk-1.1.dist-info/WHEEL
engagesdk-1.1.dist-info/top_level.txt
engagesdk-1.1.dist-info/RECORD
